kdlines/__init__.py
kdlines/kdlines.py
kdlines-0.1.dist-info/LICENSE
kdlines-0.1.dist-info/METADATA
kdlines-0.1.dist-info/WHEEL
kdlines-0.1.dist-info/top_level.txt
kdlines-0.1.dist-info/RECORD
