Metadata-Version: 2.1
Name: kdlines
Version: 0.1
Summary: Kernel density estimation and heatmap visualisation on many lines, time series or 2D data using scikit-learn.
Home-page: https://github.com/rhkarls/kdlines
License: MIT
Project-URL: Bug Tracker, https://github.com/rhkarls/kdlines/issues
Platform: UNKNOWN
Classifier: License :: OSI Approved :: MIT License
Classifier: Programming Language :: Python :: 3
Classifier: Programming Language :: Python :: 3.8
Classifier: Programming Language :: Python :: 3.9
Classifier: Programming Language :: Python :: 3.10
Requires-Python: >=3.8
License-File: LICENSE
Requires-Dist: scikit-learn
Requires-Dist: numpy
Requires-Dist: matplotlib
